pyscnet/__init__.py
pyscnet/main.py
pyscnet/BuildNet/__init__.py
pyscnet/BuildNet/gne_dockercaller.py
pyscnet/BuildNet/Docker_App/CORR/Dockerfile
pyscnet/BuildNet/Docker_App/CORR/run_corr.r
pyscnet/BuildNet/Docker_App/GENIE3/Dockerfile
pyscnet/BuildNet/Docker_App/GENIE3/requirements.txt
pyscnet/BuildNet/Docker_App/GENIE3/run_genie3.py
pyscnet/BuildNet/Docker_App/GRNBOOST2/Dockerfile
pyscnet/BuildNet/Docker_App/GRNBOOST2/requirements.txt
pyscnet/BuildNet/Docker_App/GRNBOOST2/run_grnboost2.py
pyscnet/BuildNet/Docker_App/PIDC/Dockerfile
pyscnet/BuildNet/Docker_App/PIDC/run_pidc.jl
pyscnet/BuildNet/Docker_App/SCNODE2VEC/Dockerfile
pyscnet/BuildNet/Docker_App/SCNODE2VEC/requirements.txt
pyscnet/BuildNet/Docker_App/SCNODE2VEC/run_scnode2vec.py
pyscnet/NetEnrich/__init__.py
pyscnet/NetEnrich/_de_bruijn.py
pyscnet/NetEnrich/_ensemble_classifier.py
pyscnet/NetEnrich/_graph_fusion.py
pyscnet/NetEnrich/_random_walk.py
pyscnet/NetEnrich/graph_toolkit.py
pyscnet/Plotting/__init__.py
pyscnet/Plotting/geneHeatmap.py
pyscnet/Plotting/show_net.py
pyscnet/Preprocessing/__init__.py
pyscnet/Preprocessing/gnetdata.py
pyscnet/Rshiny/.Rhistory
pyscnet/Rshiny/app.R
pyscnet/Rshiny/server.R
pyscnet/Rshiny/ui.R
pyscnet-0.0.3.dist-info/LICENSE
pyscnet-0.0.3.dist-info/METADATA
pyscnet-0.0.3.dist-info/WHEEL
pyscnet-0.0.3.dist-info/top_level.txt
pyscnet-0.0.3.dist-info/RECORD
